MANIFEST.in
README.md
VERSION.txt
requirements.txt
setup.py
django_hosted_chrome_extension.egg-info/PKG-INFO
django_hosted_chrome_extension.egg-info/SOURCES.txt
django_hosted_chrome_extension.egg-info/dependency_links.txt
django_hosted_chrome_extension.egg-info/not-zip-safe
django_hosted_chrome_extension.egg-info/top_level.txt
hosted_chrome_extension/__init__.py
hosted_chrome_extension/admin.py
hosted_chrome_extension/apps.py
hosted_chrome_extension/models.py
hosted_chrome_extension/tests.py
hosted_chrome_extension/urls.py
hosted_chrome_extension/views.py
hosted_chrome_extension/migrations/0001_initial.py
hosted_chrome_extension/migrations/__init__.py
testing/__init__.py
testing/asgi.py
testing/settings.py
testing/urls.py
testing/wsgi.py