Metadata-Version: 1.0
Name: django-hosted-chrome-extension
Version: 1.0.1
Summary: Drop-in module for a privately hosted chrome extension.
Home-page: https://github.com/matix-io/django-hosted-chrome-extension
Author: Connor Bode
Author-email: connor@matix.io
License: MIT
Platform: UNKNOWN
